Workbook

Sheet LBO Model
B1: The Wendy's Company (NASDAQ: WEN) — Leveraged Buyout (LBO) Model
B2: Hypothetical Take-Private | Sponsor: Trian Fund Management (largest shareholder, exploring take-private per FT June 2026) | Valuation Date: 6/19/2026 | All figures USD millions unless noted
B4: Assumptions | G4: Financials | K4: Capital Structure
B5: Entry ($mm) | G5: LTM Financials | L5: Amount | M5: Cost
B6: LTM EBITDA | C6: 544 | G6: Revenue | H6: 2246 | K6: Bank Debt (Term Loan B) | L6: 1500 | M6: 0.075 | O6: Source: WEN Q4 2024 Earnings Release 2/13/2025 (ir.wendys.com) — FY2024 Adjusted EBITDA $543.6mm
B7: EBITDA Multiple | C7: 9.5 | G7: EBITDA | H7: 544 | K7: Senior Secured Notes | L7: 800 | M7: 0.0875 | O7: Source: WEN 10-K FY2024 (filed 2/13/2025, SEC EDGAR CIK 0000030697) — Revenue $2,246mm
B8: Enterprise Value | C8: =C6*C7 -> 5168 | G8: D&A | H8: 162 | O8: D&A est. ~$162mm: derived from WEN FY2024 operating profit reconciliation
B9: Existing Net Debt | C9: 2401 | G9: CapEx | H9: 94 | K9: For Reference | O9: Net Debt: WEN total debt ~$2,700mm (Trefis, 12/29/2024) minus cash $299mm (Yahoo Finance, 6/2026)
B10: Equity Value | C10: =C8-C9 -> 2767 | G10: NWC Change | H10: 0 | K10: IRR | L10: =Returns!C28 -> 0.13481241 | O10: CapEx $94.4mm: Trefis / WEN 10-K FY2024; NWC ~$0 (asset-light franchise model)
B12: Fees & Expenses | C12: 150
B14: Exit ($mm) | G14: Operating Assumptions
B15: EBITDA Multiple | C15: 10 | G15: Revenue Growth | H15: 0.03
G16: YoY EBITDA Margin Expansion | H16: 0.005
G17: Tax Rate | H17: 0.26
B19: Sources and Uses
B20: Sources | G20: Uses
C21: Amount | D21: xEBITDA | E21: % Capital | H21: Amount | I21: xEBITDA | J21: % Total Uses
B22: Bank Debt (Term Loan B) | C22: =L6 -> 1500 | D22: =C22/C6 -> 2.7573529 | E22: =C22/(C25+C26) -> 0.17994242 | G22: Equity Purchase Price | H22: =C10 -> 2767 | I22: =H22/C6 -> 5.0863971 | J22: =H22/H29 -> 0.52030839
B23: Senior Secured Notes | C23: =L7 -> 800 | D23: =C23/C6 -> 1.4705882 | E23: =C23/(C25+C26) -> 0.09596929 | G23: Refinance Existing Net Debt | H23: =C9 -> 2401 | I23: =H23/C6 -> 4.4136029 | J23: =H23/H29 -> 0.45148552
B24: Total Debt | C24: =C22+C23 -> 2300 | D24: =C24/C6 -> 4.2279412 | E24: =C24/(C25+C26) -> 0.27591171
B25: Sponsor Equity | C25: =H29-C24 -> 3018 | D25: =C25/C6 -> 5.5477941 | E25: =C25/(C24+C25) -> 0.56750658 | G25: Fees & Expenses | H25: =C12 -> 150 | I25: =H25/C6 -> 0.27573529 | J25: =H25/H29 -> 0.028206093
B26: Total Sources | C26: =C24+C25 -> 5318 | D26: =C26/C6 -> 9.7757353 | E26: =IF(ABS(C26-H29)<1,"✓ Balanced","⚠ CHECK") -> ✓ Balanced
G29: Total Uses | H29: =H22+H23+H25 -> 5318 | I29: =H29/C6 -> 9.7757353 | J29: =IF(ABS(C26-H29)<1,"✓","⚠") -> ✓
B31: DATA SOURCES: LTM EBITDA $543.6mm — Wendy's Q4 & FY2024 Earnings Release (2/13/2025, ir.wendys.com). Revenue $2,246mm — WEN Form 10-K FY2024 (SEC EDGAR CIK 0000030697, filed 2/13/2025). CapEx $94.4mm — Trefis/WEN 10-K FY2024. D&A ~$162mm — estimated from operating profit bridge.
B32: Net Debt: WEN total debt ~$2,700mm (Trefis, as of 12/29/2024) minus cash $298.7mm (Yahoo Finance, 6/17/2026) = ~$2,401mm net debt. Shares ~200.5mm; stock price $6.95 (MacroTrends, 6/17/2026). Entry 9.5x EV/EBITDA — ~30% premium to current trading ~10x but on normalised earnings; Trian Fund confirmed exploring take-private per FT reporting, June 2026.

Sheet Income Statement
B1: The Wendy's Company — Pro Forma Income Statement & Debt Schedule
B2: All figures USD millions | LTM 2024A = actual | 2025E–2029E = projected | Inputs flow from LBO Model tab
C4: LTM 2024A | D4: 2025E | E4: 2026E | F4: 2027E | G4: 2028E | H4: 2029E
B5: INCOME STATEMENT
B6: Revenue ($mm) | C6: 2246 | D6: =C6*(1+'LBO Model'!H15) -> 2313.38 | E6: =D6*(1+'LBO Model'!H15) -> 2382.7814 | F6: =E6*(1+'LBO Model'!H15) -> 2454.2648 | G6: =F6*(1+'LBO Model'!H15) -> 2527.8928 | H6: =G6*(1+'LBO Model'!H15) -> 2603.7296 | J6: Revenue $2,246mm: WEN 10-K FY2024 (SEC EDGAR CIK 0000030697, filed 2/13/2025)
B7: Adjusted EBITDA ($mm) | C7: 544 | D7: =D6*(C7/C6+'LBO Model'!H16) -> 571.8869 | E7: =E6*(D7/D6+'LBO Model'!H16) -> 600.95741 | F7: =F6*(E7/E6+'LBO Model'!H16) -> 631.25746 | G7: =G6*(F7/F6+'LBO Model'!H16) -> 662.83465 | H7: =H6*(G7/G6+'LBO Model'!H16) -> 695.73834 | J7: Adj. EBITDA $543.6mm: WEN Q4&FY2024 Earnings Release (2/13/2025, ir.wendys.com); grows via 3% revenue growth + 50bps margin expansion/yr
B8: EBITDA Margin % | C8: =C7/C6 -> 0.24220837 | D8: =D7/D6 -> 0.24720837 | E8: =E7/E6 -> 0.25220837 | F8: =F7/F6 -> 0.25720837 | G8: =G7/G6 -> 0.26220837 | H8: =H7/H6 -> 0.26720837
B9: Less: D&A | C9: 162 | D9: =C9*1.03 -> 166.86 | E9: =D9*1.03 -> 171.8658 | F9: =E9*1.03 -> 177.02177 | G9: =F9*1.03 -> 182.33243 | H9: =G9*1.03 -> 187.8024 | J9: D&A ~$162mm: estimated from WEN FY2024 operating profit bridge; grows 3%/yr
B10: EBIT ($mm) | C10: =C7-C9 -> 382 | D10: =D7-D9 -> 405.0269 | E10: =E7-E9 -> 429.09161 | F10: =F7-F9 -> 454.23569 | G10: =G7-G9 -> 480.50222 | H10: =H7-H9 -> 507.93594
B11: Less: Interest Expense | C11: =-('LBO Model'!L6*'LBO Model'!M6+'LBO Model'!L7*'LBO Model'!M7) -> -182.5 | D11: =-(C33*'LBO Model'!M6+C34*'LBO Model'!M7) -> -182.5 | E11: =-(D33*'LBO Model'!M6+D34*'LBO Model'!M7) -> -170.75875 | F11: =-(E33*'LBO Model'!M6+E34*'LBO Model'!M7) -> -158.02256 | G11: =-(F33*'LBO Model'!M6+F34*'LBO Model'!M7) -> -144.23937 | H11: =-(G33*'LBO Model'!M6+G34*'LBO Model'!M7) -> -129.35485
B12: EBT (Pre-Tax Income) | C12: =C10+C11 -> 199.5 | D12: =D10+D11 -> 222.5269 | E12: =E10+E11 -> 258.33286 | F12: =F10+F11 -> 296.21313 | G12: =G10+G11 -> 336.26285 | H12: =H10+H11 -> 378.58109
B13: Less: Taxes | C13: =IF(C12>0,-C12*'LBO Model'!H17,0) -> -51.87 | D13: =IF(D12>0,-D12*'LBO Model'!H17,0) -> -57.856994 | E13: =IF(E12>0,-E12*'LBO Model'!H17,0) -> -67.166544 | F13: =IF(F12>0,-F12*'LBO Model'!H17,0) -> -77.015413 | G13: =IF(G12>0,-G12*'LBO Model'!H17,0) -> -87.428342 | H13: =IF(H12>0,-H12*'LBO Model'!H17,0) -> -98.431083
B14: Net Income ($mm) | C14: =C12+C13 -> 147.63 | D14: =D12+D13 -> 164.66991 | E14: =E12+E13 -> 191.16632 | F14: =F12+F13 -> 219.19771 | G14: =G12+G13 -> 248.83451 | H14: =H12+H13 -> 280.15
B16: UNLEVERED FREE CASH FLOW
B17: EBITDA | C17: =C7 -> 544 | D17: =D7 -> 571.8869 | E17: =E7 -> 600.95741 | F17: =F7 -> 631.25746 | G17: =G7 -> 662.83465 | H17: =H7 -> 695.73834
B18: Less: Cash CapEx | C18: -94 | D18: =C18*1.02 -> -95.88 | E18: =D18*1.02 -> -97.7976 | F18: =E18*1.02 -> -99.753552 | G18: =F18*1.02 -> -101.74862 | H18: =G18*1.02 -> -103.7836 | J18: CapEx $94.4mm FY2024: Trefis/WEN 10-K FY2024; grows 2%/yr in projections
B19: Less: Change in NWC | C19: =0 -> 0 | D19: =0 -> 0 | E19: =0 -> 0 | F19: =0 -> 0 | G19: =0 -> 0 | H19: =0 -> 0
B20: Less: Cash Taxes | C20: =C13 -> -51.87 | D20: =D13 -> -57.856994 | E20: =E13 -> -67.166544 | F20: =F13 -> -77.015413 | G20: =G13 -> -87.428342 | H20: =H13 -> -98.431083
B21: Unlevered FCF (for Debt Service) | C21: =C17+C18+C19+C20 -> 398.13 | D21: =D17+D18+D19+D20 -> 418.14991 | E21: =E17+E18+E19+E20 -> 435.99327 | F21: =F17+F18+F19+F20 -> 454.4885 | G21: =G17+G18+G19+G20 -> 473.65768 | H21: =H17+H18+H19+H20 -> 493.52366
B23: DEBT SCHEDULE
C24: LTM 2024A | D24: 2025E | E24: 2026E | F24: 2027E | G24: 2028E | H24: 2029E
B25: Bank Debt — Beginning of Year | C25: ='LBO Model'!L6 -> 1500 | D25: =C33 -> 1500 | E25: =D33 -> 1343.45 | F25: =E33 -> 1173.6342 | G25: =F33 -> 989.85825 | H25: =G33 -> 791.39797
B26: Mandatory Amortization (1%/yr) | C26: =0 -> 0 | D26: =-'LBO Model'!L6*0.01 -> -15 | E26: =-'LBO Model'!L6*0.01 -> -15 | F26: =-'LBO Model'!L6*0.01 -> -15 | G26: =-'LBO Model'!L6*0.01 -> -15 | H26: =-'LBO Model'!L6*0.01 -> -15 | J26: Mandatory amort: 1% of original Bank Debt principal per year (standard TLB term)
B27: Cash Flow Sweep (50% Excess FCF) | C27: =0 -> 0 | D27: =MIN(-0.5*(D21+D11*(1-'LBO Model'!H17)),0) -> -141.54995 | E27: =MIN(-0.5*(E21+E11*(1-'LBO Model'!H17)),0) -> -154.8159 | F27: =MIN(-0.5*(F21+F11*(1-'LBO Model'!H17)),0) -> -168.7759 | G27: =MIN(-0.5*(G21+G11*(1-'LBO Model'!H17)),0) -> -183.46028 | H27: =MIN(-0.5*(H21+H11*(1-'LBO Model'!H17)),0) -> -198.90053 | J27: 50% cash sweep of levered FCF applied to Bank Debt prepayment (standard PE debt structure)
B28: Bank Debt — End of Year | C28: =C25 -> 1500 | D28: =D25+D26+D27 -> 1343.45 | E28: =E25+E26+E27 -> 1173.6342 | F28: =F25+F26+F27 -> 989.85825 | G28: =G25+G26+G27 -> 791.39797 | H28: =H25+H26+H27 -> 577.49744
B30: Senior Secured Notes — Beginning of Year | C30: ='LBO Model'!L7 -> 800 | D30: =C34 -> 800 | E30: =D34 -> 800 | F30: =E34 -> 800 | G30: =F34 -> 800 | H30: =G34 -> 800
B31: Senior Secured Notes — End of Year (Bullet) | C31: ='LBO Model'!L7 -> 800 | D31: ='LBO Model'!L7 -> 800 | E31: ='LBO Model'!L7 -> 800 | F31: ='LBO Model'!L7 -> 800 | G31: ='LBO Model'!L7 -> 800 | H31: ='LBO Model'!L7 -> 800 | J31: Senior Secured Notes modeled as bullet maturity — no scheduled annual paydown
B33: [Bank Debt EOY – helper row for interest calc] | C33: =C28 -> 1500 | D33: =D28 -> 1343.45 | E33: =E28 -> 1173.6342 | F33: =F28 -> 989.85825 | G33: =G28 -> 791.39797 | H33: =H28 -> 577.49744
B34: [Notes EOY – helper row for interest calc] | C34: =C31 -> 800 | D34: =D31 -> 800 | E34: =E31 -> 800 | F34: =F31 -> 800 | G34: =G31 -> 800 | H34: =H31 -> 800
B36: CREDIT METRICS
C37: LTM 2024A | D37: 2025E | E37: 2026E | F37: 2027E | G37: 2028E | H37: 2029E
B38: Total Debt / EBITDA | C38: =(C28+C31)/C7 -> 4.2279412 | D38: =(D28+D31)/D7 -> 3.7480314 | E38: =(E28+E31)/E7 -> 3.2841498 | F38: =(F28+F31)/F7 -> 2.8353855 | G38: =(G28+G31)/G7 -> 2.4008974 | H38: =(H28+H31)/H7 -> 1.9799073
B39: Net Debt / EBITDA (assume $100mm min cash) | C39: =(C28+C31-100)/C7 -> 4.0441176 | D39: =(D28+D31-100)/D7 -> 3.5731716 | E39: =(E28+E31-100)/E7 -> 3.1177486 | F39: =(F28+F31-100)/F7 -> 2.6769715 | G39: =(G28+G31-100)/G7 -> 2.2500302 | H39: =(H28+H31-100)/H7 -> 1.8361751
B40: Interest Coverage (EBITDA / Interest Expense) | C40: =IF(C11<0,C7/ABS(C11),0) -> 2.9808219 | D40: =IF(D11<0,D7/ABS(D11),0) -> 3.1336268 | E40: =IF(E11<0,E7/ABS(E11),0) -> 3.5193359 | F40: =IF(F11<0,F7/ABS(F11),0) -> 3.99473 | G40: =IF(G11<0,G7/ABS(G11),0) -> 4.5953796 | H40: =IF(H11<0,H7/ABS(H11),0) -> 5.3785254

Sheet Returns
B1: The Wendy's Company — LBO Returns Analysis (5-Year Hold)
B2: All figures USD millions | Entry 2026 → Exit 2031 (5-year hold) | Exit via IPO or strategic sale
C4: Entry (Yr 0) | D4: Year 1 2025E | E4: Year 2 2026E | F4: Year 3 2027E | G4: Year 4 2028E | H4: Year 5 2029E
B5: EXIT VALUATION (YEAR 5 — 2029E)
B6: Exit Year EBITDA ($mm) | D6: ='Income Statement'!D7 -> 571.8869 | E6: ='Income Statement'!E7 -> 600.95741 | F6: ='Income Statement'!F7 -> 631.25746 | G6: ='Income Statement'!G7 -> 662.83465 | H6: ='Income Statement'!H7 -> 695.73834
B7: Exit EV / EBITDA Multiple | H7: ='LBO Model'!C15 -> 10
B8: Exit Enterprise Value ($mm) | H8: =H6*H7 -> 6957.3834
B9: Less: Total Debt at Exit | H9: =-('Income Statement'!H28+'Income Statement'!H31) -> -1377.4974
B10: Plus: Minimum Cash ($mm) | H10: 100
B11: Exit Equity Value ($mm) | H11: =H8+H9+H10 -> 5679.8859
B13: SPONSOR CASH FLOWS
B14: Equity Invested at Entry (Year 0, outflow) | C14: =-'LBO Model'!C25 -> -3018 | D14: 0 | E14: 0 | F14: 0 | G14: 0
B15: Dividends / Distributions to Sponsor | C15: 0 | D15: 0 | E15: 0 | F15: 0 | G15: 0 | H15: 0
B16: Exit Proceeds (Year 5, inflow) | C16: 0 | D16: 0 | E16: 0 | F16: 0 | G16: 0 | H16: =H11 -> 5679.8859
B17: Net Sponsor Cash Flow ($mm) | C17: =C14+C15+C16 -> -3018 | D17: =D14+D15+D16 -> 0 | E17: =E14+E15+E16 -> 0 | F17: =F14+F15+F16 -> 0 | G17: =G14+G15+G16 -> 0 | H17: =H14+H15+H16 -> 5679.8859
B19: RETURNS SUMMARY
B20: Equity Invested ($mm) | H20: =ABS(C14) -> 3018
B21: Exit Equity Value ($mm) | H21: =H11 -> 5679.8859
B22: Hold Period (Years) | H22: 5
B23: Money-on-Money Multiple (MoM) | H23: =H21/H20 -> 1.8820033
B24: Gross IRR (5-Year Hold) | H24: =IFERROR(IRR(C17:H17),0) -> 0.13481241
B25: Entry EV / EBITDA Multiple | H25: ='LBO Model'!C7 -> 9.5
B26: Exit EV / EBITDA Multiple | H26: ='LBO Model'!C15 -> 10
B27: Entry Total Debt / EBITDA | H27: ='Income Statement'!C38 -> 4.2279412
B28: Exit Total Debt / EBITDA | C28: =H24 -> 0.13481241 | H28: ='Income Statement'!H38 -> 1.9799073
B30: IRR SENSITIVITY — Entry EV/EBITDA Multiple vs. Exit EV/EBITDA Multiple
B31: Entry ↓ / Exit → | C31: 8.0x | D31: 9.0x | E31: 10.0x | F31: 11.0x | G31: 12.0x
B32: 8.5x | C32: =IFERROR((('Income Statement'!H7*8-('Income Statement'!H28+'Income Statement'!H31)+100)/('LBO Model'!C6*8.5-'LBO Model'!C9-'LBO Model'!C12))^(1/5)-1,0) -> 0.15648335 | D32: =IFERROR((('Income Statement'!H7*9-('Income Statement'!H28+'Income Statement'!H31)+100)/('LBO Model'!C6*8.5-'LBO Model'!C9-'LBO Model'!C12))^(1/5)-1,0) -> 0.19178611 | E32: =IFERROR((('Income Statement'!H7*10-('Income Statement'!H28+'Income Statement'!H31)+100)/('LBO Model'!C6*8.5-'LBO Model'!C9-'LBO Model'!C12))^(1/5)-1,0) -> 0.2233425 | F32: =IFERROR((('Income Statement'!H7*11-('Income Statement'!H28+'Income Statement'!H31)+100)/('LBO Model'!C6*8.5-'LBO Model'!C9-'LBO Model'!C12))^(1/5)-1,0) -> 0.25194336 | G32: =IFERROR((('Income Statement'!H7*12-('Income Statement'!H28+'Income Statement'!H31)+100)/('LBO Model'!C6*8.5-'LBO Model'!C9-'LBO Model'!C12))^(1/5)-1,0) -> 0.27814687
B33: 9.0x | C33: =IFERROR((('Income Statement'!H7*8-('Income Statement'!H28+'Income Statement'!H31)+100)/('LBO Model'!C6*9-'LBO Model'!C9-'LBO Model'!C12))^(1/5)-1,0) -> 0.12831581 | D33: =IFERROR((('Income Statement'!H7*9-('Income Statement'!H28+'Income Statement'!H31)+100)/('LBO Model'!C6*9-'LBO Model'!C9-'LBO Model'!C12))^(1/5)-1,0) -> 0.16275873 | E33: =IFERROR((('Income Statement'!H7*10-('Income Statement'!H28+'Income Statement'!H31)+100)/('LBO Model'!C6*9-'LBO Model'!C9-'LBO Model'!C12))^(1/5)-1,0) -> 0.19354653 | F33: =IFERROR((('Income Statement'!H7*11-('Income Statement'!H28+'Income Statement'!H31)+100)/('LBO Model'!C6*9-'LBO Model'!C9-'LBO Model'!C12))^(1/5)-1,0) -> 0.22145079 | G33: =IFERROR((('Income Statement'!H7*12-('Income Statement'!H28+'Income Statement'!H31)+100)/('LBO Model'!C6*9-'LBO Model'!C9-'LBO Model'!C12))^(1/5)-1,0) -> 0.24701608
B34: 9.5x | C34: =IFERROR((('Income Statement'!H7*8-('Income Statement'!H28+'Income Statement'!H31)+100)/('LBO Model'!C6*9.5-'LBO Model'!C9-'LBO Model'!C12))^(1/5)-1,0) -> 0.10382061 | D34: =IFERROR((('Income Statement'!H7*9-('Income Statement'!H28+'Income Statement'!H31)+100)/('LBO Model'!C6*9.5-'LBO Model'!C9-'LBO Model'!C12))^(1/5)-1,0) -> 0.13751579 | E34: =IFERROR((('Income Statement'!H7*10-('Income Statement'!H28+'Income Statement'!H31)+100)/('LBO Model'!C6*9.5-'LBO Model'!C9-'LBO Model'!C12))^(1/5)-1,0) -> 0.1676352 | F34: =IFERROR((('Income Statement'!H7*11-('Income Statement'!H28+'Income Statement'!H31)+100)/('LBO Model'!C6*9.5-'LBO Model'!C9-'LBO Model'!C12))^(1/5)-1,0) -> 0.19493367 | G34: =IFERROR((('Income Statement'!H7*12-('Income Statement'!H28+'Income Statement'!H31)+100)/('LBO Model'!C6*9.5-'LBO Model'!C9-'LBO Model'!C12))^(1/5)-1,0) -> 0.21994395
B35: 10.0x | C35: =IFERROR((('Income Statement'!H7*8-('Income Statement'!H28+'Income Statement'!H31)+100)/('LBO Model'!C6*10-'LBO Model'!C9-'LBO Model'!C12))^(1/5)-1,0) -> 0.082205499 | D35: =IFERROR((('Income Statement'!H7*9-('Income Statement'!H28+'Income Statement'!H31)+100)/('LBO Model'!C6*10-'LBO Model'!C9-'LBO Model'!C12))^(1/5)-1,0) -> 0.11524085 | E35: =IFERROR((('Income Statement'!H7*10-('Income Statement'!H28+'Income Statement'!H31)+100)/('LBO Model'!C6*10-'LBO Model'!C9-'LBO Model'!C12))^(1/5)-1,0) -> 0.14477046 | F35: =IFERROR((('Income Statement'!H7*11-('Income Statement'!H28+'Income Statement'!H31)+100)/('LBO Model'!C6*10-'LBO Model'!C9-'LBO Model'!C12))^(1/5)-1,0) -> 0.17153437 | G35: =IFERROR((('Income Statement'!H7*12-('Income Statement'!H28+'Income Statement'!H31)+100)/('LBO Model'!C6*10-'LBO Model'!C9-'LBO Model'!C12))^(1/5)-1,0) -> 0.1960549
B36: 10.5x | C36: =IFERROR((('Income Statement'!H7*8-('Income Statement'!H28+'Income Statement'!H31)+100)/('LBO Model'!C6*10.5-'LBO Model'!C9-'LBO Model'!C12))^(1/5)-1,0) -> 0.062904744 | D36: =IFERROR((('Income Statement'!H7*9-('Income Statement'!H28+'Income Statement'!H31)+100)/('LBO Model'!C6*10.5-'LBO Model'!C9-'LBO Model'!C12))^(1/5)-1,0) -> 0.095350925 | E36: =IFERROR((('Income Statement'!H7*10-('Income Statement'!H28+'Income Statement'!H31)+100)/('LBO Model'!C6*10.5-'LBO Model'!C9-'LBO Model'!C12))^(1/5)-1,0) -> 0.12435388 | F36: =IFERROR((('Income Statement'!H7*11-('Income Statement'!H28+'Income Statement'!H31)+100)/('LBO Model'!C6*10.5-'LBO Model'!C9-'LBO Model'!C12))^(1/5)-1,0) -> 0.15064047 | G36: =IFERROR((('Income Statement'!H7*12-('Income Statement'!H28+'Income Statement'!H31)+100)/('LBO Model'!C6*10.5-'LBO Model'!C9-'LBO Model'!C12))^(1/5)-1,0) -> 0.17472368
B38: NOTES: IRR = Internal Rate of Return on sponsor equity over 5-year hold. Entry equity = EV – existing net debt ($2,401mm) – fees ($150mm). Exit equity = Exit EV (EBITDA × multiple) – remaining debt at exit + $100mm min cash. Sensitivity table uses compound-growth approximation ((Exit/Entry)^(1/5)−1). Base case (9.5x entry / 10.0x exit) highlighted yellow. No mid-hold dividends modeled. Wendy's current public dividend ($0.25/share/quarter ~$200mm/yr) assumed terminated at close.
