Workbook

Sheet Summary
A1: COSTCO WHOLESALE CORPORATION (NASDAQ: COST) - TRADING COMPARABLES ANALYSIS
A2: Daniel Wahba | Analysis Date: July 7, 2026 | Peer Set: Walmart (WMT), Target (TGT), BJ's Wholesale (BJ)
B5: COST SNAPSHOT (7/7/2026) | F5: IMPLIED VALUATION (PEER MEAN MULTIPLES)
B6: Current Share Price | C6: 947.5 | F6: Implied Price - EV/EBITDA Method | G6: =='Trading Multiples'!C24
B7: Market Capitalization ($mm) | C7: 420200 | F7: Implied Price - EV/Revenue Method | G7: =='Trading Multiples'!C25
B8: Enterprise Value ($mm) | C8: 408430 | F8: Implied Price - P/E Method | G8: =='Trading Multiples'!C26
B9: TTM Revenue ($mm) | C9: 293590 | F9: Average Implied Price (Peer Comps) | G9: =='Trading Multiples'!C27
B10: TTM EBITDA ($mm) | C10: 13790 | F10: Actual Price vs. Peer-Implied Price | G10: =='Trading Multiples'!C28
B11: TTM P/E | C11: 47.66
B12: TTM EV/EBITDA | C12: 29.62
B14: KEY FINDING: THE 'QUALITY PREMIUM'
B15: - Applying peer (WMT/TGT/BJ) mean trading multiples to Costco's own EBITDA, revenue, and EPS implies a share price of roughly half Costco's actual .50 trading price -- Costco trades at a large, persistent premium to every large-format retail peer on every multiple.
B17: - This is not a mispricing signal; it reflects a genuine quality premium the market assigns to Costco's business model: membership-fee revenue (high-margin, highly recurring, ~90%+ renewal rates) effectively subsidizes wafer-thin, deliberately-capped merchandise margins, producing more predictable, less cyclical earnings than a traditional big-box retailer.
B19: - BJ's Wholesale is the closest structural comp (same membership-club model) and trades far closer to Costco's growth profile than Walmart/Target, yet still at roughly half Costco's EV/EBITDA multiple -- suggesting the market further distinguishes Costco's scale, brand, and international runway even within the club-retail category.
B21: - Comps are best used here as a relative-value cross-check and a lens on 'what the market is paying for' rather than a standalone price target -- consistent with how this multiple set is explicitly framed as a sense-check, not a valuation conclusion, on the Trading Multiples tab.
B24: COLOR KEY USED THROUGHOUT THIS MODEL
B25: Blue font | C25: Hardcoded input / assumption (sourced from market data)
B26: Black font | C26: Formula calculated within the same worksheet
B27: Green font | C27: Formula linking to another worksheet in this workbook
B28: Yellow highlight | C28: Key output cell
B31: WORKBOOK NAVIGATION
B32: Summary | C32: This page - snapshot, implied valuation output, and key finding.
B33: Comp Set & Financial Data | C33: Share price, shares, market cap, EV, revenue, EBITDA, net income for COST + 3 peers.
B34: Trading Multiples | C34: EV/Revenue, EV/EBITDA, P/E per company, peer mean/median, and implied COST valuation.
B35: Sources | C35: Full bibliography of every data source used in this model.

Sheet Comp Set & Financial Data
A1: TRADING COMPARABLES - COMP SET & FINANCIAL DATA
A2: Daniel Wahba | $ in millions except per-share data | TTM figures and market data as of 7/7/2026 (stockanalysis.com)
A4: Ticker | B4: Company | C4: Share Price | D4: Diluted Shares (mm) | E4: Market Cap | F4: Net Debt / (Cash) | G4: Enterprise Value | H4: Revenue (TTM) | I4: EBITDA (TTM) | J4: EBITDA Margin | K4: Net Income (TTM) | L4: Net Margin | M4: Diluted EPS (TTM) | N4: Rev. Growth (Fwd 3-Yr)
A6: COST | B6: Costco Wholesale Corp. | C6: 947.5 | D6: ==E6/C6 | E6: 420200 | F6: ==G6-E6 | G6: 408430 | H6: 293590 | I6: 13790 | J6: ==I6/H6 | K6: 8840 | L6: ==K6/H6 | M6: 19.88 | N6: 0.0832
A7: WMT | B7: Walmart Inc. | C7: 111.54 | D7: ==E7/C7 | E7: 887640 | F7: ==G7-E7 | G7: 952460 | H7: 725310 | I7: 44840 | J7: ==I7/H7 | K7: 22740 | L7: ==K7/H7 | M7: 2.84 | N7: 0.05
A8: TGT | B8: Target Corp. | C8: 127.55 | D8: ==E8/C8 | E8: 57930 | F8: ==G8-E8 | G8: 73670 | H8: 106380 | I8: 8340 | J8: ==I8/H8 | K8: 3450 | L8: ==K8/H8 | M8: 7.57 | N8: 0.0325
A9: BJ | B9: BJ's Wholesale Club Holdings | C9: 87.52 | D9: ==E9/C9 | E9: 11180 | F9: ==G9-E9 | G9: 14010 | H9: 21970 | I9: 1120 | J9: ==I9/H9 | K9: 571.34 | L9: ==K9/H9 | M9: 4.35 | N9: 0.0756

Sheet Trading Multiples
A1: TRADING COMPARABLES - MULTIPLES & IMPLIED VALUATION
A2: Daniel Wahba | All multiples derived from the Comp Set & Financial Data tab
A4: Ticker | B4: Company | C4: EV / Revenue | D4: EV / EBITDA | E4: P/E (TTM) | F4: P/E (Fwd)
A6: =='Comp Set & Financial Data'!A6 | B6: =='Comp Set & Financial Data'!B6 | C6: =='Comp Set & Financial Data'!G6/'Comp Set & Financial Data'!H6 | D6: =='Comp Set & Financial Data'!G6/'Comp Set & Financial Data'!I6 | E6: =='Comp Set & Financial Data'!C6/'Comp Set & Financial Data'!M6 | F6: 43.27
A7: =='Comp Set & Financial Data'!A7 | B7: =='Comp Set & Financial Data'!B7 | C7: =='Comp Set & Financial Data'!G7/'Comp Set & Financial Data'!H7 | D7: =='Comp Set & Financial Data'!G7/'Comp Set & Financial Data'!I7 | E7: =='Comp Set & Financial Data'!C7/'Comp Set & Financial Data'!M7 | F7: 37.42
A8: =='Comp Set & Financial Data'!A8 | B8: =='Comp Set & Financial Data'!B8 | C8: =='Comp Set & Financial Data'!G8/'Comp Set & Financial Data'!H8 | D8: =='Comp Set & Financial Data'!G8/'Comp Set & Financial Data'!I8 | E8: =='Comp Set & Financial Data'!C8/'Comp Set & Financial Data'!M8 | F8: 14.93
A9: =='Comp Set & Financial Data'!A9 | B9: =='Comp Set & Financial Data'!B9 | C9: =='Comp Set & Financial Data'!G9/'Comp Set & Financial Data'!H9 | D9: =='Comp Set & Financial Data'!G9/'Comp Set & Financial Data'!I9 | E9: =='Comp Set & Financial Data'!C9/'Comp Set & Financial Data'!M9 | F9: 18.88
B11: Peer Mean (WMT / TGT / BJ, excl. COST) | C11: ==AVERAGE(C7:C9) | D11: ==AVERAGE(D7:D9) | E11: ==AVERAGE(E7:E9) | F11: ==AVERAGE(F7:F9)
B12: Peer Median (WMT / TGT / BJ, excl. COST) | C12: ==MEDIAN(C7:C9) | D12: ==MEDIAN(D7:D9) | E12: ==MEDIAN(E7:E9) | F12: ==MEDIAN(F7:F9)
A15: IMPLIED COST VALUATION (Applying Peer MEAN Multiples to COST's Own Financials)
A16: This is a relative-value sense-check, not a standalone price target -- see Summary tab for interpretation.
A18: Method | B18: Peer Mean Multiple | C18: COST Metric Applied | D18: Implied Enterprise Value | E18: (-) Net Debt / (Cash) | F18: Implied Equity Value | G18: / Diluted Shares (mm) | H18: = Implied Share Price
A19: EV / EBITDA Method | B19: ==D11 | C19: =='Comp Set & Financial Data'!I6 | D19: ==B19*C19 | E19: =='Comp Set & Financial Data'!F6 | F19: ==D19-E19 | G19: =='Comp Set & Financial Data'!D6 | H19: ==F19/G19
A20: EV / Revenue Method | B20: ==C11 | C20: =='Comp Set & Financial Data'!H6 | D20: ==B20*C20 | E20: =='Comp Set & Financial Data'!F6 | F20: ==D20-E20 | G20: =='Comp Set & Financial Data'!D6 | H20: ==F20/G20
A21: P/E Method (direct to equity) | B21: ==E11 | C21: =='Comp Set & Financial Data'!M6 | D21: n/a - direct to price | E21: n/a | F21: n/a | G21: n/a | H21: ==B21*C21
A23: SUMMARY OUTPUT (referenced by the Summary tab)
A24: EV / EBITDA Method - Implied Share Price | C24: ==H19
A25: EV / Revenue Method - Implied Share Price | C25: ==H20
A26: P/E Method - Implied Share Price | C26: ==H21
A27: Average Implied Share Price (3 Methods) | C27: ==AVERAGE(C24:C26)
A28: Actual COST Price vs. Peer-Implied Average (Premium) | C28: =='Comp Set & Financial Data'!C6/C27-1

Sheet Sources
A1: SOURCES & METHODOLOGY NOTES
A2: Daniel Wahba | Costco Wholesale Corporation (NASDAQ: COST) - Trading Comparables Analysis
A4: # | B4: Source | C4: Used For
A5: 1 | B5: stockanalysis.com/stocks/cost/statistics/ - accessed 7/7/2026 | C5: COST share price, market cap, EV, TTM revenue/EBITDA/net income/EPS, total debt, cash.
A6: 2 | B6: stockanalysis.com/stocks/wmt/statistics/ - accessed 7/7/2026 | C6: WMT share price, market cap, EV, TTM revenue/EBITDA/net income/EPS, forward P/E, revenue growth forecast.
A7: 3 | B7: stockanalysis.com/stocks/tgt/statistics/ - accessed 7/7/2026 | C7: TGT share price, market cap, EV, TTM revenue/EBITDA/net income/EPS, forward P/E, revenue growth forecast.
A8: 4 | B8: stockanalysis.com/stocks/bj/statistics/ - accessed 7/7/2026 | C8: BJ share price, market cap, EV, TTM revenue/EBITDA/net income/EPS, forward P/E, revenue growth forecast.
A10: METHODOLOGY / DERIVATION NOTES
A11: - Diluted Shares Outstanding for each company is derived as Market Cap / Share Price (both sourced from the same stockanalysis.com snapshot), rather than pulling a separately-reported share count -- this keeps each company's price, market cap, and share count fully internally consistent as of the same data pull.
A13: - Net Debt / (Cash) is derived as Enterprise Value - Market Cap for all four companies. For Costco, this reconciles to within rounding of Total Debt ($8,230mm) less Cash ($20,000mm) = ($11,770mm), an independent cross-check sourced from the same statistics page.
A15: - Forward P/E is a directly-sourced market-consensus statistic (not derived from a separately-modeled forward EPS figure) and is shown for reference; it is not used in the Implied COST Valuation build, which relies only on TTM (trailing-twelve-month) financials for methodological consistency.
A17: - The peer set (Walmart, Target, BJ's Wholesale) excludes Costco itself from the 'Peer Mean' / 'Peer Median' calculations, per standard trading-comps methodology -- the subject company is never included in the multiple set used to value it.
A19: - The Implied COST Valuation section is explicitly framed as a relative-value sense-check, not a price target: Costco trades at a structural premium to every peer on every multiple, which this model attributes to its membership-fee-driven earnings quality rather than treating it as a valuation error (see Summary tab).
