Workbook

Sheet Summary
A1: COSTCO WHOLESALE CORPORATION (NASDAQ: COST) - THREE-STATEMENT OPERATING MODEL
A2: Daniel Wahba | Model Date: July 7, 2026 | Fiscal Year Ends Last Sunday in August
B5: COMPANY SNAPSHOT | F5: KEY MODEL OUTPUTS (FY2030E)
B6: Ticker / Exchange | C6: COST / Nasdaq Global Select Market | F6: FY2030E Revenue () | G6: =='Income Statement'!J10
B7: Sector | C7: Consumer Staples - Warehouse Clubs & Superstores | F7: FY2030E EBITDA () | G7: =='Income Statement'!J16
B8: Fiscal Year End | C8: August 30, 2025 (FY2025A) | F8: FY2030E Net Income () | G8: =='Income Statement'!J21
B9: Current Share Price | C9: 947.5 | F9: FY2030E Diluted EPS | G9: =='Income Statement'!J22
B10: Diluted Shares Outstanding (mm) | C10: 445 | F10: Revenue CAGR (FY25A-FY30E) | G10: ==(('Income Statement'!J10/'Income Statement'!E10)^(1/5))-1
B11: Market Capitalization ($mm) | C11: 420200 | F11: EPS CAGR (FY25A-FY30E) | G11: ==(('Income Statement'!J22/'Income Statement'!E22)^(1/5))-1
B12: Total Debt ($mm) | C12: 8230
B13: Net Cash Position ($mm) | C13: 11770
B16: MODEL METHODOLOGY & KEY ASSUMPTIONS
B17: - Revenue growth tapers from 8.3% (FY2026E, anchored to FactSet/TIKR 3-yr consensus CAGR of 8.32% per stockanalysis.com) to 6.5% (FY2030E) as the warehouse base matures and comp growth normalizes.
B19: - Gross margin held near FY2025A actual (12.84%) with modest 25bps/yr drift toward 13.1% by FY2030E - consistent with Costco's publicly stated policy of capping merchandise margins to drive membership renewal, per management commentary in FY2025 10-K.
B21: - SG&A ratio improves modestly (9.07% to 8.80% of revenue) reflecting operating leverage on a growing warehouse base; effective tax rate held flat at 25.0% (vs. FY2025A actual of 25.14%).
B23: - No circularity: interest income & cash are NOT modeled as interdependent (interest income held as a direct assumption, not calculated off the projected cash balance) - a deliberate simplification to keep the model fully non-iterative and error-free.
B25: - Dividend payout ratio held at 27.0% of net income (vs. FY2025A actual of 26.95%, excluding the one-time .0bn special dividend paid in January 2024); share buybacks held flat at ~,300mm/yr, near the FY2025A run-rate of ,296mm.
B27: - Balance sheet 'Other' asset/liability lines are derived as residuals (Total less itemized line items) from reported totals - each is explained on the Sources tab; these residuals are held flat as a % of revenue or COGS through the forecast.
B30: COLOR KEY USED THROUGHOUT THIS MODEL
B31: Blue font | C31: Hardcoded input / assumption (sourced from filings, market data, or analyst judgment)
B32: Black font | C32: Formula calculated within the same worksheet
B33: Green font | C33: Formula linking to another worksheet in this workbook
B34: Yellow highlight | C34: Key output cell
B37: WORKBOOK NAVIGATION
B38: Summary | C38: This page - executive overview, key outputs, methodology, and navigation.
B39: Assumptions | C39: All revenue, margin, working-capital, and capital-allocation drivers with sourcing notes.
B40: Income Statement | C40: FY2022A-FY2025A actuals and FY2026E-FY2030E forecast, formula-driven from Assumptions.
B41: Balance Sheet | C41: FY2022A-FY2025A actuals and FY2026E-FY2030E forecast, with a balance check row.
B42: Cash Flow Statement | C42: Indirect-method CFO/CFI/CFF, fully linked to the Income Statement and Balance Sheet.
B43: Sources | C43: Full bibliography of every data source and methodology note used in this model.

Sheet Assumptions
A1: COSTCO WHOLESALE CORPORATION - MODEL ASSUMPTIONS
A2: Daniel Wahba | All forecast-driver assumptions for FY2026E-FY2030E. Historical ratios (source baseline) shown in the Notes column.
B4: FY2022A | C4: FY2023A | D4: FY2024A | E4: FY2025A | F4: FY2026E | G4: FY2027E | H4: FY2028E | I4: FY2029E | J4: FY2030E | K4: NOTES / SOURCE
A6: REVENUE & MARGIN ASSUMPTIONS
A8: Revenue Growth % | F8: 0.083 | G8: 0.08 | H8: 0.075 | I8: 0.07 | J8: 0.065 | K8: FY26E-28E anchored to FactSet/TIKR 3-yr consensus CAGR of 8.32% (stockanalysis.com, 7/7/2026); tapered further for FY29E-30E per typical deceleration modeling.
A9: Gross Margin % | F9: 0.129 | G9: 0.1295 | H9: 0.13 | I9: 0.1305 | J9: 0.131 | K9: FY2025A actual = 12.84% ($35,349mm / $275,235mm). Modest 25bps/yr drift assumed from e-commerce & ancillary mix; Costco caps merchandise margins by policy per FY2025 10-K.
A10: SG&A % of Revenue | F10: 0.09 | G10: 0.0895 | H10: 0.089 | I10: 0.0885 | J10: 0.088 | K10: FY2025A actual = 9.07% ($24,966mm / $275,235mm). Gradual opex leverage assumed on a growing warehouse base.
A11: D&A % of Revenue | F11: 0.0088 | G11: 0.0089 | H11: 0.009 | I11: 0.0091 | J11: 0.0092 | K11: FY2025A actual = 0.88% ($2,426mm / $275,235mm). Ticks up slightly with an expanding PP&E base from continued warehouse openings.
A12: Effective Tax Rate % | F12: 0.25 | G12: 0.25 | H12: 0.25 | I12: 0.25 | J12: 0.25 | K12: FY2025A actual = 25.14% ($2,719mm / $10,818mm); held flat at a round 25.0%.
A13: Interest Expense ($mm) | F13: 155 | G13: 155 | H13: 155 | I13: 155 | J13: 150 | K13: FY2025A actual = $154mm. Held roughly flat - Costco carries minimal debt ($5.7bn LT debt vs. $77bn total assets).
A14: Interest Income & Other, Net ($mm) | F14: 620 | G14: 660 | H14: 700 | I14: 740 | J14: 780 | K14: FY2025A actual (derived) = $589mm = Pretax Income - Operating Income + Interest Expense, per 10-K IS presentation. Grown ~6%/yr with rising net cash balance (deliberately NOT formula-linked to the projected cash balance, to avoid circularity).
A16: CAPITAL ALLOCATION ASSUMPTIONS
A18: Capex % of Revenue | F18: 0.02 | G18: 0.02 | H18: 0.021 | I18: 0.021 | J18: 0.021 | K18: FY2025A actual = 2.00% ($5,498mm / $275,235mm). Held roughly flat - continued warehouse & e-commerce fulfillment capacity expansion.
A19: Dividend Payout Ratio % | F19: 0.27 | G19: 0.27 | H19: 0.27 | I19: 0.27 | J19: 0.27 | K19: FY2025A actual = 26.95% ($2,183mm / $8,099mm NI), EXCLUDING the one-time $9,041mm special dividend paid Jan-2024 (FY2024). Held flat at 27.0%.
A20: Share Buybacks ($mm) | F20: 1300 | G20: 1300 | H20: 1300 | I20: 1300 | J20: 1300 | K20: FY2025A actual = $1,296mm. Held flat near the recent run-rate.
A21: Diluted Shares Outstanding (mm) | F21: 445 | G21: 445 | H21: 445 | I21: 445 | J21: 445 | K21: FY2022A-FY2025A actual range = 444-445mm (stable). Buybacks assumed to roughly offset SBC-driven share issuance, consistent with the 4-yr historical pattern.
A22: Stock-Based Comp % of Revenue | F22: 0.0031 | G22: 0.0031 | H22: 0.0031 | I22: 0.0031 | J22: 0.0031 | K22: FY2025A actual = 0.31% ($860mm / $275,235mm). Held flat.
A24: WORKING CAPITAL & BALANCE SHEET ASSUMPTIONS (held flat at FY2025A ratios)
A26: Accounts Receivable % of Revenue | F26: 0.0116 | G26: 0.0116 | H26: 0.0116 | I26: 0.0116 | J26: 0.0116 | K26: FY2025A actual = 1.16% ($3,203mm / $275,235mm).
A27: Merchandise Inventory % of COGS | F27: 0.0755 | G27: 0.0755 | H27: 0.0755 | I27: 0.0755 | J27: 0.0755 | K27: FY2025A actual = 7.55% ($18,116mm / $239,886mm).
A28: Other Current Assets % of Revenue | F28: 0.0065 | G28: 0.0065 | H28: 0.0065 | I28: 0.0065 | J28: 0.0065 | K28: FY2025A actual (derived residual) = 0.65% ($1,777mm / $275,235mm).
A29: Accounts Payable % of COGS | F29: 0.0825 | G29: 0.0825 | H29: 0.0825 | I29: 0.0825 | J29: 0.0825 | K29: FY2025A actual = 8.25% ($19,783mm / $239,886mm).
A30: Accrued Expenses % of Revenue | F30: 0.0189 | G30: 0.0189 | H30: 0.0189 | I30: 0.0189 | J30: 0.0189 | K30: FY2025A actual = 1.89% ($5,205mm / $275,235mm).
A31: Other Current Liabilities % of Revenue | F31: 0.044 | G31: 0.044 | H31: 0.044 | I31: 0.044 | J31: 0.044 | K31: FY2025A actual (derived residual, incl. deferred membership fees & accrued payroll) = 4.40% ($12,120mm / $275,235mm).
A32: Other Long-Term Assets % of Revenue | F32: 0.0148 | G32: 0.0148 | H32: 0.0148 | I32: 0.0148 | J32: 0.0148 | K32: FY2025A actual (derived residual) = 1.48% ($4,085mm / $275,235mm).
A33: Other Long-Term Liabilities % of Revenue | F33: 0.0186 | G33: 0.0186 | H33: 0.0186 | I33: 0.0186 | J33: 0.0186 | K33: FY2025A actual (derived residual) = 1.86% ($5,114mm / $275,235mm).
A34: Short-Term Investments ($mm) | F34: 1123 | G34: 1123 | H34: 1123 | I34: 1123 | J34: 1123 | K34: FY2025A actual = $1,123mm. Held flat (immaterial balance).
A35: Long-Term Debt ($mm) | F35: 5713 | G35: 5713 | H35: 5713 | I35: 5713 | J35: 5713 | K35: FY2025A actual = $5,713mm. Held flat - no major issuance or repayment assumed.
A36: Current Portion of LT Debt ($mm) | F36: 0 | G36: 0 | H36: 0 | I36: 0 | J36: 0 | K36: FY2024A-FY2025A actual = $0 (no near-term maturities disclosed). Held at $0.

Sheet Income Statement
A1: COSTCO WHOLESALE CORPORATION - INCOME STATEMENT
A2: Daniel Wahba | $ in millions, except per-share data | FY2022A-FY2025A actual, FY2026E-FY2030E forecast
B4: FY2022A | C4: FY2023A | D4: FY2024A | E4: FY2025A | F4: FY2026E | G4: FY2027E | H4: FY2028E | I4: FY2029E | J4: FY2030E
A10: Revenue | B10: 226954 | C10: 242290 | D10: 254453 | E10: 275235 | F10: ==E10*(1+Assumptions!F8) | G10: ==F10*(1+Assumptions!G8) | H10: ==G10*(1+Assumptions!H8) | I10: ==H10*(1+Assumptions!I8) | J10: ==I10*(1+Assumptions!J8)
A11: Cost of Merchandise Sold | B11: 199382 | C11: 212586 | D11: 222358 | E11: 239886 | F11: ==F10*(1-Assumptions!F9) | G11: ==G10*(1-Assumptions!G9) | H11: ==H10*(1-Assumptions!H9) | I11: ==I10*(1-Assumptions!I9) | J11: ==J10*(1-Assumptions!J9)
A12: Gross Profit | B12: ==B10-B11 | C12: ==C10-C11 | D12: ==D10-D11 | E12: ==E10-E11 | F12: ==F10-F11 | G12: ==G10-G11 | H12: ==H10-H11 | I12: ==I10-I11 | J12: ==J10-J11
A13: Selling, General & Administrative | B13: 19779 | C13: 21590 | D13: 22810 | E13: 24966 | F13: ==F10*Assumptions!F10 | G13: ==G10*Assumptions!G10 | H13: ==H10*Assumptions!H10 | I13: ==I10*Assumptions!I10 | J13: ==J10*Assumptions!J10
A14: Operating Income (EBIT) | B14: ==B12-B13 | C14: ==C12-C13 | D14: ==D12-D13 | E14: ==E12-E13 | F14: ==F12-F13 | G14: ==G12-G13 | H14: ==H12-H13 | I14: ==I12-I13 | J14: ==J12-J13
A15: (+) Depreciation & Amortization | B15: 1900 | C15: 2077 | D15: 2237 | E15: 2426 | F15: ==F10*Assumptions!F11 | G15: ==G10*Assumptions!G11 | H15: ==H10*Assumptions!H11 | I15: ==I10*Assumptions!I11 | J15: ==J10*Assumptions!J11
A16: EBITDA | B16: ==B14+B15 | C16: ==C14+C15 | D16: ==D14+D15 | E16: ==E14+E15 | F16: ==F14+F15 | G16: ==G14+G15 | H16: ==H14+H15 | I16: ==I14+I15 | J16: ==J14+J15
A17: Interest Expense | B17: -158 | C17: -160 | D17: -169 | E17: -154 | F17: ==Assumptions!F13*-1 | G17: ==Assumptions!G13*-1 | H17: ==Assumptions!H13*-1 | I17: ==Assumptions!I13*-1 | J17: ==Assumptions!J13*-1
A18: Interest Income & Other, Net | B18: 205 | C18: 533 | D18: 624 | E18: 589 | F18: ==Assumptions!F14 | G18: ==Assumptions!G14 | H18: ==Assumptions!H14 | I18: ==Assumptions!I14 | J18: ==Assumptions!J14
A19: Pretax Income | B19: ==B14+B17+B18 | C19: ==C14+C17+C18 | D19: ==D14+D17+D18 | E19: ==E14+E17+E18 | F19: ==F14+F17+F18 | G19: ==G14+G17+G18 | H19: ==H14+H17+H18 | I19: ==I14+I17+I18 | J19: ==J14+J17+J18
A20: Income Tax Expense | B20: 1925 | C20: 2195 | D20: 2373 | E20: 2719 | F20: ==F19*Assumptions!F12 | G20: ==G19*Assumptions!G12 | H20: ==H19*Assumptions!H12 | I20: ==I19*Assumptions!I12 | J20: ==J19*Assumptions!J12
A21: Net Income | B21: ==B19-B20 | C21: ==C19-C20 | D21: ==D19-D20 | E21: ==E19-E20 | F21: ==F19-F20 | G21: ==G19-G20 | H21: ==H19-H20 | I21: ==I19-I20 | J21: ==J19-J20
A22: Diluted EPS | B22: 13.14 | C22: 14.16 | D22: 16.56 | E22: 18.21 | F22: ==F21/F23 | G22: ==G21/G23 | H22: ==H21/H23 | I22: ==I21/I23 | J22: ==J21/J23
A23: Diluted Shares Outstanding (mm) | B23: 445 | C23: 444 | D23: 445 | E23: 445 | F23: ==Assumptions!F21 | G23: ==Assumptions!G21 | H23: ==Assumptions!H21 | I23: ==Assumptions!I21 | J23: ==Assumptions!J21
A25: MEMO: KEY RATIOS
A26: Revenue Growth % | C26: ==C10/B10-1 | D26: ==D10/C10-1 | E26: ==E10/D10-1 | F26: ==F10/E10-1 | G26: ==G10/F10-1 | H26: ==H10/G10-1 | I26: ==I10/H10-1 | J26: ==J10/I10-1
A27: Gross Margin % | C27: ==C12/C10 | D27: ==D12/D10 | E27: ==E12/E10 | F27: ==F12/F10 | G27: ==G12/G10 | H27: ==H12/H10 | I27: ==I12/I10 | J27: ==J12/J10
A28: Operating Margin % | C28: ==C14/C10 | D28: ==D14/D10 | E28: ==E14/E10 | F28: ==F14/F10 | G28: ==G14/G10 | H28: ==H14/H10 | I28: ==I14/I10 | J28: ==J14/J10
A29: Net Margin % | C29: ==C21/C10 | D29: ==D21/D10 | E29: ==E21/E10 | F29: ==F21/F10 | G29: ==G21/G10 | H29: ==H21/H10 | I29: ==I21/I10 | J29: ==J21/J10

Sheet Balance Sheet
A1: COSTCO WHOLESALE CORPORATION - BALANCE SHEET
A2: Daniel Wahba | $ in millions | FY2022A-FY2025A actual, FY2026E-FY2030E forecast
B4: FY2022A | C4: FY2023A | D4: FY2024A | E4: FY2025A | F4: FY2026E | G4: FY2027E | H4: FY2028E | I4: FY2029E | J4: FY2030E
A8: ASSETS
A9: Cash & Cash Equivalents | B9: 10203 | C9: 13700 | D9: 9906 | E9: 14161 | F9: =='Cash Flow Statement'!F28 | G9: =='Cash Flow Statement'!G28 | H9: =='Cash Flow Statement'!H28 | I9: =='Cash Flow Statement'!I28 | J9: =='Cash Flow Statement'!J28
A10: Short-Term Investments | B10: 846 | C10: 1534 | D10: 1238 | E10: 1123 | F10: ==Assumptions!F34 | G10: ==Assumptions!G34 | H10: ==Assumptions!H34 | I10: ==Assumptions!I34 | J10: ==Assumptions!J34
A11: Accounts Receivable | B11: 2241 | C11: 2285 | D11: 2721 | E11: 3203 | F11: =='Income Statement'!F10*Assumptions!F26 | G11: =='Income Statement'!G10*Assumptions!G26 | H11: =='Income Statement'!H10*Assumptions!H26 | I11: =='Income Statement'!I10*Assumptions!I26 | J11: =='Income Statement'!J10*Assumptions!J26
A12: Merchandise Inventories | B12: 17907 | C12: 16651 | D12: 18647 | E12: 18116 | F12: =='Income Statement'!F11*Assumptions!F27 | G12: =='Income Statement'!G11*Assumptions!G27 | H12: =='Income Statement'!H11*Assumptions!H27 | I12: =='Income Statement'!I11*Assumptions!I27 | J12: =='Income Statement'!J11*Assumptions!J27
A13: Other Current Assets | B13: 1499 | C13: 1709 | D13: 1734 | E13: 1777 | F13: =='Income Statement'!F10*Assumptions!F28 | G13: =='Income Statement'!G10*Assumptions!G28 | H13: =='Income Statement'!H10*Assumptions!H28 | I13: =='Income Statement'!I10*Assumptions!I28 | J13: =='Income Statement'!J10*Assumptions!J28
A14: Total Current Assets | B14: ==SUM(B9:B13) | C14: ==SUM(C9:C13) | D14: ==SUM(D9:D13) | E14: ==SUM(E9:E13) | F14: ==SUM(F9:F13) | G14: ==SUM(G9:G13) | H14: ==SUM(H9:H13) | I14: ==SUM(I9:I13) | J14: ==SUM(J9:J13)
A15: Property & Equipment, Net | B15: 27420 | C15: 29397 | D15: 31649 | E15: 34634 | F15: ==E15-'Cash Flow Statement'!F16-'Income Statement'!F15 | G15: ==F15-'Cash Flow Statement'!G16-'Income Statement'!G15 | H15: ==G15-'Cash Flow Statement'!H16-'Income Statement'!H15 | I15: ==H15-'Cash Flow Statement'!I16-'Income Statement'!I15 | J15: ==I15-'Cash Flow Statement'!J16-'Income Statement'!J15
A16: Other Long-Term Assets | B16: 4050 | C16: 3718 | D16: 3936 | E16: 4085 | F16: =='Income Statement'!F10*Assumptions!F32 | G16: =='Income Statement'!G10*Assumptions!G32 | H16: =='Income Statement'!H10*Assumptions!H32 | I16: =='Income Statement'!I10*Assumptions!I32 | J16: =='Income Statement'!J10*Assumptions!J32
A17: TOTAL ASSETS | B17: ==B14+B15+B16 | C17: ==C14+C15+C16 | D17: ==D14+D15+D16 | E17: ==E14+E15+E16 | F17: ==F14+F15+F16 | G17: ==G14+G15+G16 | H17: ==H14+H15+H16 | I17: ==I14+I15+I16 | J17: ==J14+J15+J16
A19: LIABILITIES
A20: Accounts Payable | B20: 17848 | C20: 17483 | D20: 19421 | E20: 19783 | F20: =='Income Statement'!F11*Assumptions!F29 | G20: =='Income Statement'!G11*Assumptions!G29 | H20: =='Income Statement'!H11*Assumptions!H29 | I20: =='Income Statement'!I11*Assumptions!I29 | J20: =='Income Statement'!J11*Assumptions!J29
A21: Accrued Salaries, Benefits & Other | B21: 4381 | C21: 4278 | D21: 4794 | E21: 5205 | F21: =='Income Statement'!F10*Assumptions!F30 | G21: =='Income Statement'!G10*Assumptions!G30 | H21: =='Income Statement'!H10*Assumptions!H30 | I21: =='Income Statement'!I10*Assumptions!I30 | J21: =='Income Statement'!J10*Assumptions!J30
A22: Current Portion of Long-Term Debt | B22: 73 | C22: 1081 | D22: 0 | E22: 0 | F22: ==Assumptions!F36 | G22: ==Assumptions!G36 | H22: ==Assumptions!H36 | I22: ==Assumptions!I36 | J22: ==Assumptions!J36
A23: Other Current Liabilities | B23: 9696 | C23: 10741 | D23: 11249 | E23: 12120 | F23: =='Income Statement'!F10*Assumptions!F31 | G23: =='Income Statement'!G10*Assumptions!G31 | H23: =='Income Statement'!H10*Assumptions!H31 | I23: =='Income Statement'!I10*Assumptions!I31 | J23: =='Income Statement'!J10*Assumptions!J31
A24: Total Current Liabilities | B24: ==SUM(B20:B23) | C24: ==SUM(C20:C23) | D24: ==SUM(D20:D23) | E24: ==SUM(E20:E23) | F24: ==SUM(F20:F23) | G24: ==SUM(G20:G23) | H24: ==SUM(H20:H23) | I24: ==SUM(I20:I23) | J24: ==SUM(J20:J23)
A25: Long-Term Debt | B25: 6484 | C25: 5377 | D25: 5794 | E25: 5713 | F25: ==Assumptions!F35 | G25: ==Assumptions!G35 | H25: ==Assumptions!H35 | I25: ==Assumptions!I35 | J25: ==Assumptions!J35
A26: Other Long-Term Liabilities | B26: 5037 | C26: 4976 | D26: 4951 | E26: 5114 | F26: =='Income Statement'!F10*Assumptions!F33 | G26: =='Income Statement'!G10*Assumptions!G33 | H26: =='Income Statement'!H10*Assumptions!H33 | I26: =='Income Statement'!I10*Assumptions!I33 | J26: =='Income Statement'!J10*Assumptions!J33
A27: TOTAL LIABILITIES | B27: ==B24+B25+B26 | C27: ==C24+C25+C26 | D27: ==D24+D25+D26 | E27: ==E24+E25+E26 | F27: ==F24+F25+F26 | G27: ==G24+G25+G26 | H27: ==H24+H25+H26 | I27: ==I24+I25+I26 | J27: ==J24+J25+J26
A29: SHAREHOLDERS' EQUITY
A30: Total Shareholders' Equity | B30: 20642 | C30: 25058 | D30: 23622 | E30: 29164 | F30: ==E30+'Income Statement'!F21+'Cash Flow Statement'!F20+'Cash Flow Statement'!F21+'Cash Flow Statement'!F11 | G30: ==F30+'Income Statement'!G21+'Cash Flow Statement'!G20+'Cash Flow Statement'!G21+'Cash Flow Statement'!G11 | H30: ==G30+'Income Statement'!H21+'Cash Flow Statement'!H20+'Cash Flow Statement'!H21+'Cash Flow Statement'!H11 | I30: ==H30+'Income Statement'!I21+'Cash Flow Statement'!I20+'Cash Flow Statement'!I21+'Cash Flow Statement'!I11 | J30: ==I30+'Income Statement'!J21+'Cash Flow Statement'!J20+'Cash Flow Statement'!J21+'Cash Flow Statement'!J11
A32: TOTAL LIABILITIES & SHAREHOLDERS' EQUITY | B32: ==B27+B30 | C32: ==C27+C30 | D32: ==D27+D30 | E32: ==E27+E30 | F32: ==F27+F30 | G32: ==G27+G30 | H32: ==H27+H30 | I32: ==I27+I30 | J32: ==J27+J30
A33: Balance Check (Assets - Liab. & Equity) | B33: ==B17-B32 | C33: ==C17-C32 | D33: ==D17-D32 | E33: ==E17-E32 | F33: ==F17-F32 | G33: ==G17-G32 | H33: ==H17-H32 | I33: ==I17-I32 | J33: ==J17-J32

Sheet Cash Flow Statement
A1: COSTCO WHOLESALE CORPORATION - CASH FLOW STATEMENT
A2: Daniel Wahba | $ in millions | FY2022A-FY2025A actual, FY2026E-FY2030E forecast | Indirect method
B4: FY2022A | C4: FY2023A | D4: FY2024A | E4: FY2025A | F4: FY2026E | G4: FY2027E | H4: FY2028E | I4: FY2029E | J4: FY2030E
A8: OPERATING ACTIVITIES
A9: Net Income | B9: =='Income Statement'!B21 | C9: =='Income Statement'!C21 | D9: =='Income Statement'!D21 | E9: =='Income Statement'!E21 | F9: =='Income Statement'!F21 | G9: =='Income Statement'!G21 | H9: =='Income Statement'!H21 | I9: =='Income Statement'!I21 | J9: =='Income Statement'!J21
A10: (+) Depreciation & Amortization | B10: =='Income Statement'!B15 | C10: =='Income Statement'!C15 | D10: =='Income Statement'!D15 | E10: =='Income Statement'!E15 | F10: =='Income Statement'!F15 | G10: =='Income Statement'!G15 | H10: =='Income Statement'!H15 | I10: =='Income Statement'!I15 | J10: =='Income Statement'!J15
A11: (+) Stock-Based Compensation | B11: 724 | C11: 774 | D11: 818 | E11: 860 | F11: =='Income Statement'!F10*Assumptions!F22 | G11: =='Income Statement'!G10*Assumptions!G22 | H11: =='Income Statement'!H10*Assumptions!H22 | I11: =='Income Statement'!I10*Assumptions!I22 | J11: =='Income Statement'!J10*Assumptions!J22
A12: (+/-) Change in Net Working Capital | B12: -1545 | C12: 1018 | D12: 611 | E12: 1764 | F12: ==-(('Balance Sheet'!F11-'Balance Sheet'!E11)+('Balance Sheet'!F12-'Balance Sheet'!E12)+('Balance Sheet'!F13-'Balance Sheet'!E13))+(('Balance Sheet'!F20-'Balance Sheet'!E20)+('Balance Sheet'!F21-'Balance Sheet'!E21)+('Balance Sheet'!F23-'Balance Sheet'!E23)) | G12: ==-(('Balance Sheet'!G11-'Balance Sheet'!F11)+('Balance Sheet'!G12-'Balance Sheet'!F12)+('Balance Sheet'!G13-'Balance Sheet'!F13))+(('Balance Sheet'!G20-'Balance Sheet'!F20)+('Balance Sheet'!G21-'Balance Sheet'!F21)+('Balance Sheet'!G23-'Balance Sheet'!F23)) | H12: ==-(('Balance Sheet'!H11-'Balance Sheet'!G11)+('Balance Sheet'!H12-'Balance Sheet'!G12)+('Balance Sheet'!H13-'Balance Sheet'!G13))+(('Balance Sheet'!H20-'Balance Sheet'!G20)+('Balance Sheet'!H21-'Balance Sheet'!G21)+('Balance Sheet'!H23-'Balance Sheet'!G23)) | I12: ==-(('Balance Sheet'!I11-'Balance Sheet'!H11)+('Balance Sheet'!I12-'Balance Sheet'!H12)+('Balance Sheet'!I13-'Balance Sheet'!H13))+(('Balance Sheet'!I20-'Balance Sheet'!H20)+('Balance Sheet'!I21-'Balance Sheet'!H21)+('Balance Sheet'!I23-'Balance Sheet'!H23)) | J12: ==-(('Balance Sheet'!J11-'Balance Sheet'!I11)+('Balance Sheet'!J12-'Balance Sheet'!I12)+('Balance Sheet'!J13-'Balance Sheet'!I13))+(('Balance Sheet'!J20-'Balance Sheet'!I20)+('Balance Sheet'!J21-'Balance Sheet'!I21)+('Balance Sheet'!J23-'Balance Sheet'!I23))
A13: (+/-) Other Operating Activities, Net (hist.); Chg. in Other LT Assets/Liab. (fcst.) | B13: 398 | C13: 907 | D13: 306 | E13: 186 | F13: ==-(('Balance Sheet'!F16-'Balance Sheet'!E16))+(('Balance Sheet'!F26-'Balance Sheet'!E26)) | G13: ==-(('Balance Sheet'!G16-'Balance Sheet'!F16))+(('Balance Sheet'!G26-'Balance Sheet'!F26)) | H13: ==-(('Balance Sheet'!H16-'Balance Sheet'!G16))+(('Balance Sheet'!H26-'Balance Sheet'!G26)) | I13: ==-(('Balance Sheet'!I16-'Balance Sheet'!H16))+(('Balance Sheet'!I26-'Balance Sheet'!H26)) | J13: ==-(('Balance Sheet'!J16-'Balance Sheet'!I16))+(('Balance Sheet'!J26-'Balance Sheet'!I26))
A14: Cash Flow from Operations | B14: ==SUM(B9:B13) | C14: ==SUM(C9:C13) | D14: ==SUM(D9:D13) | E14: ==SUM(E9:E13) | F14: ==SUM(F9:F13) | G14: ==SUM(G9:G13) | H14: ==SUM(H9:H13) | I14: ==SUM(I9:I13) | J14: ==SUM(J9:J13)
A15: INVESTING ACTIVITIES
A16: Capital Expenditures | B16: -3891 | C16: -4323 | D16: -4710 | E16: -5498 | F16: ==-('Income Statement'!F10*Assumptions!F18) | G16: ==-('Income Statement'!G10*Assumptions!G18) | H16: ==-('Income Statement'!H10*Assumptions!H18) | I16: ==-('Income Statement'!I10*Assumptions!I18) | J16: ==-('Income Statement'!J10*Assumptions!J18)
A17: Cash Flow from Investing (Capex; hist. incl. ST investment activity) | B17: -3915 | C17: -4972 | D17: -4409 | E17: -5311 | F17: ==F16 | G17: ==G16 | H17: ==H16 | I17: ==I16 | J17: ==J16
A19: FINANCING ACTIVITIES
A20: Dividends Paid | B20: -1498 | C20: -1251 | D20: -9041 | E20: -2183 | F20: ==-('Income Statement'!F21*Assumptions!F19) | G20: ==-('Income Statement'!G21*Assumptions!G19) | H20: ==-('Income Statement'!H21*Assumptions!H19) | I20: ==-('Income Statement'!I21*Assumptions!I19) | J20: ==-('Income Statement'!J21*Assumptions!J19)
A21: Share Buybacks | B21: -802 | C21: -979 | D21: -1015 | E21: -1296 | F21: ==-(Assumptions!F20) | G21: ==-(Assumptions!G20) | H21: ==-(Assumptions!H20) | I21: ==-(Assumptions!I20) | J21: ==-(Assumptions!J20)
A22: Debt Repayment & Other Financing, Net | B22: -1983 | C22: -384 | D22: -708 | E22: -296 | F22: 0 | G22: 0 | H22: 0 | I22: 0 | J22: 0
A23: Cash Flow from Financing | B23: ==SUM(B20:B22) | C23: ==SUM(C20:C22) | D23: ==SUM(D20:D22) | E23: ==SUM(E20:E22) | F23: ==SUM(F20:F22) | G23: ==SUM(G20:G22) | H23: ==SUM(H20:H22) | I23: ==SUM(I20:I22) | J23: ==SUM(J20:J22)
A25: Net Change in Cash | B25: ==B14+B17+B23 | C25: ==C14+C17+C23 | D25: ==D14+D17+D23 | E25: ==E14+E17+E23 | F25: ==F14+F17+F23 | G25: ==G14+G17+G23 | H25: ==H14+H17+H23 | I25: ==I14+I17+I23 | J25: ==J14+J17+J23
A26: Effect of Exchange Rates & Other | B26: 0 | C26: 15 | D26: 40 | E26: 6 | F26: 0 | G26: 0 | H26: 0 | I26: 0 | J26: 0
A27: Cash - Beginning of Period | B27: 11009 | C27: ==B28 | D27: ==C28 | E27: ==D28 | F27: ==E28 | G27: ==F28 | H27: ==G28 | I27: ==H28 | J27: ==I28
A28: Cash - Ending of Period | B28: ==B27+B25+B26 | C28: ==C27+C25+C26 | D28: ==D27+D25+D26 | E28: ==E27+E25+E26 | F28: ==F27+F25+F26 | G28: ==G27+G25+G26 | H28: ==H27+H25+H26 | I28: ==I27+I25+I26 | J28: ==J27+J25+J26

Sheet Sources
A1: SOURCES & METHODOLOGY NOTES
A2: Daniel Wahba | Costco Wholesale Corporation (NASDAQ: COST) - Three-Statement Operating Model
A4: # | B4: Source | C4: Used For
A5: 1 | B5: Costco Wholesale Corp. FY2025 Form 10-K, filed 9/25/2025, SEC CIK 0000909832 (fiscal year ended 8/31/2025) | C5: Primary source for all FY2025A figures; company description; fiscal year-end convention.
A6: 2 | B6: stockanalysis.com/stocks/cost/financials/ - Income Statement, accessed 7/7/2026 | C6: FY2022A-FY2025A Revenue, COGS, SG&A, Operating Income, Interest Expense, Pretax Income, Tax, Net Income, Diluted EPS & Shares, EBITDA.
A7: 3 | B7: stockanalysis.com/stocks/cost/financials/balance-sheet/ - Balance Sheet, accessed 7/7/2026 | C7: FY2022A-FY2025A Cash, ST Investments, AR, Inventory, Total Current Assets, PP&E, Total Assets, AP, Accrued Expenses, Current LTD, Total Current Liabilities, LT Debt, Total Liabilities, Total Equity.
A8: 4 | B8: stockanalysis.com/stocks/cost/financials/cash-flow-statement/ - Cash Flow Statement, accessed 7/7/2026 | C8: FY2022A-FY2025A Net Income, D&A, Stock-Based Comp, Working Capital Change, CFO, Capex, CFI, Dividends, Buybacks, CFF.
A9: 5 | B9: stockanalysis.com/stocks/cost/statistics/ - Key Statistics, accessed 7/7/2026 | C9: Current share price ($947.50), market cap ($420.2bn), enterprise value, total debt, cash, TTM P/E, EV/EBITDA, 3-yr revenue growth consensus (8.32%).
A10: 6 | B10: Costco Investor Relations - Q4 & Full-Year FY2025 Operating Results press release | C10: Corroboration of FY2025A net sales (+8% to $269.9bn) and membership fee revenue (+10% to $5.3bn).
A12: METHODOLOGY / DERIVATION NOTES
A13: - 'Interest Income & Other, Net' (Income Statement, historical) is derived as Pretax Income - Operating Income + Interest Expense for each fiscal year, consistent with Costco's income statement presentation, which reports interest expense and non-operating interest/other income as separate lines below operating income.
A15: - 'Other Current Assets', 'Other Long-Term Assets', 'Other Current Liabilities' (incl. deferred membership fees & accrued payroll), and 'Other Long-Term Liabilities' (Balance Sheet, historical) are each derived as the residual needed to reconcile itemized line items to Costco's reported subtotal/total for that year - i.e., Total less the sum of itemized components. This is standard practice when working from aggregated third-party financial data rather than the line-item detail in the full 10-K notes.
A17: - FY2022A shows a $5mm balance-check variance (Total Assets vs. Total Liabilities & Equity), equal to 0.008% of total assets - an immaterial rounding artifact traced to the underlying aggregated data source, not a modeling error. FY2023A-FY2025A tie exactly to $0.
A19: - 'Other Operating Activities, Net' and 'Debt Repayment & Other Financing, Net' (Cash Flow Statement, historical) are residual plugs equal to reported CFO/CFF less the itemized lines shown (e.g., deferred taxes, employee tax withholding on equity awards, and other items not separately broken out by the data source).
A21: - FY2022A 'Cash - Beginning of Period' ($11,009mm) is implied by working backward from FY2022A's known ending cash balance and net cash flow activity, since FY2021A balance sheet data was outside this build's source set.
A23: - FY2024A dividends paid of $9,041mm include a one-time special cash dividend of $15.00/share (~$6.7bn) paid January 2024, in addition to the regular quarterly dividend - this is why the FY2026E-FY2030E dividend assumption is anchored to the FY2025A payout ratio (26.95%), not FY2024A.
A25: - Forecast 'Other' balance-sheet lines, SBC, and select cash-flow items are held flat as a % of revenue/COGS at FY2025A levels - a standard simplifying assumption for a student-built model; a professional model would build each from further bottom-up detail.
A27: - The model is intentionally built with NO circular references: interest income is a direct (non-cash-linked) assumption, so the workbook calculates correctly with iterative calculation OFF.
A29: - 'Cash Flow from Investing' for FY2022A-FY2025A is the actual reported total (which includes net purchases/maturities of short-term investments, not itemized separately), and is therefore slightly larger in magnitude than 'Capital Expenditures' alone. FY2026E-FY2030E investing cash flow is modeled as Capex only (short-term investments held flat per the Assumptions tab), a disclosed simplification.
A31: - Forecast 'Total Shareholders' Equity' rolls forward as: prior equity + Net Income + Dividends Paid + Share Buybacks + Stock-Based Compensation. SBC is added back because, while it reduces Net Income (and therefore retained earnings) as a non-cash expense, the offsetting entry is a credit to Additional Paid-In Capital -- so it does not reduce total equity on a net basis. This keeps the balance sheet tying exactly in every forecast year.
A33: - For FY2026E-FY2030E, the operating cash flow line 'Chg. in Other LT Assets/Liab.' captures the year-over-year change in the Balance Sheet's 'Other Long-Term Assets' and 'Other Long-Term Liabilities' lines (both modeled as a % of revenue), so that growth in those balance-sheet items is reflected in cash flow -- without it, the balance sheet would not tie in the forecast period.
